{
   "DefinitionSource" : "",
   "Heading" : "Ukraine",
   "ImageWidth" : 0,
   "RelatedTopics" : [
      {
         "Result" : "<a href=\"https://duckduckgo.com/Ukraine\">Ukraine</a> A country in Eastern Europe, bordered by Russia to the east and northeast, Belarus to the...",
         "Icon" : {
            "URL" : "https://duckduckgo.com/i/edd533ad.png",
            "Height" : "",
            "Width" : ""
         },
         "FirstURL" : "https://duckduckgo.com/Ukraine",
         "Text" : "Ukraine A country in Eastern Europe, bordered by Russia to the east and northeast, Belarus to the..."
      },
      {
         "Result" : "<a href=\"https://duckduckgo.com/Ukrainian_Soviet_Socialist_Republic\">Ukrainian SSR</a>A sovereign Soviet socialist state and one of the fifteen constituent republics of the Soviet...",
         "Icon" : {
            "URL" : "https://duckduckgo.com/i/bf77a683.png",
            "Height" : "",
            "Width" : ""
         },
         "FirstURL" : "https://duckduckgo.com/Ukrainian_Soviet_Socialist_Republic",
         "Text" : "Ukrainian SSR A sovereign Soviet socialist state and one of the fifteen constituent republics of the Soviet..."
      },
      {
         "Result" : "<a href=\"https://duckduckgo.com/Ukrainian_People's_Republic\">Ukrainian People's Republic</a>The Ukrainian People's Republic or Ukrainian National Republic, a predecessor of modern Ukraine...",
         "Icon" : {
            "URL" : "https://duckduckgo.com/i/ce365879.jpg",
            "Height" : "",
            "Width" : ""
         },
         "FirstURL" : "https://duckduckgo.com/Ukrainian_People's_Republic",
         "Text" : "Ukrainian People's Republic The Ukrainian People's Republic or Ukrainian National Republic, a predecessor of modern Ukraine..."
      },
      {
         "Result" : "<a href=\"https://duckduckgo.com/ukraina-class_motorship\">Ukraine class motorship</a>A class of Russian river passenger ships.",
         "Icon" : {
            "URL" : "https://duckduckgo.com/i/ef5af460.jpg",
            "Height" : "",
            "Width" : ""
         },
         "FirstURL" : "https://duckduckgo.com/ukraina-class_motorship",
         "Text" : "Ukraine class motorship A class of Russian river passenger ships."
      },
      {
         "Result" : "<a href=\"https://duckduckgo.com/Bulgaria_(ship)\">Ukraina</a> A class 785/OL800 Russian river cruise ship which operated in the Volga-Don basin.",
         "Icon" : {
            "URL" : "https://duckduckgo.com/i/2f9c4713.jpg",
            "Height" : "",
            "Width" : ""
         },
         "FirstURL" : "https://duckduckgo.com/Bulgaria_(ship)",
         "Text" : "Ukraina A class 785/OL800 Russian river cruise ship which operated in the Volga-Don basin."
      },
      {
         "Result" : "<a href=\"https://duckduckgo.com/Rise_up%2C_Ukraine!\">Rise up, Ukraine!</a>\"Rise up, Ukraine!\" was a nationwide series of political protests by opposition parties...",
         "Icon" : {
            "URL" : "https://duckduckgo.com/i/bb369cd4.jpg",
            "Height" : "",
            "Width" : ""
         },
         "FirstURL" : "https://duckduckgo.com/Rise_up%2C_Ukraine!",
         "Text" : "Rise up, Ukraine! \"Rise up, Ukraine!\" was a nationwide series of political protests by opposition parties..."
      },
      {
         "Result" : "<a href=\"https://duckduckgo.com/Ukraine_%E2%80%93_Forward!\">Ukraine \u2013 Forward!</a> Political party in Ukraine.",
         "Icon" : {
            "URL" : "",
            "Height" : "",
            "Width" : ""
         },
         "FirstURL" : "https://duckduckgo.com/Ukraine_%E2%80%93_Forward!",
         "Text" : "Ukraine \u2013 Forward! Political party in Ukraine."
      },
      {
         "Result" : "<a href=\"https://duckduckgo.com/Hotel_Ukrayina\">Ukrayina</a>A four-star hotel located in central Kiev, the capital of Ukraine.",
         "Icon" : {
            "URL" : "https://duckduckgo.com/i/016730d3.jpg",
            "Height" : "",
            "Width" : ""
         },
         "FirstURL" : "https://duckduckgo.com/Hotel_Ukrayina",
         "Text" : "Ukrayina A four-star hotel located in central Kiev, the capital of Ukraine."
      },
      {
         "Result" : "<a href=\"https://duckduckgo.com/FC_Ukraina_Syracuse\">Ukraina</a> Sport club from <a href=\"https://duckduckgo.com/?q=Syracuse%2C%20New%20York\">Syracuse, New York</a>.",
         "Icon" : {
            "URL" : "",
            "Height" : "",
            "Width" : ""
         },
         "FirstURL" : "https://duckduckgo.com/FC_Ukraina_Syracuse",
         "Text" : "Ukraina Sport club from Syracuse, New York ."
      },
      {
         "Result" : "<a href=\"https://duckduckgo.com/Ukrayina_(TV_channel)\">Ukraine</a>TV Channel \"Ukraine\" is one of the most popular television channels in Ukraine.",
         "Icon" : {
            "URL" : "https://duckduckgo.com/i/a689f3fa.jpg",
            "Height" : "",
            "Width" : ""
         },
         "FirstURL" : "https://duckduckgo.com/Ukrayina_(TV_channel)",
         "Text" : "Ukraine TV Channel \"Ukraine\" is one of the most popular television channels in Ukraine."
      },
      {
         "Result" : "<a href=\"https://duckduckgo.com/Ukraine_Air_Enterprise\">Ukraine</a>A government-owned airline based in Kiev, Ukraine.",
         "Icon" : {
            "URL" : "https://duckduckgo.com/i/dap.kiev.ua.ico",
            "Height" : 16,
            "Width" : 16
         },
         "FirstURL" : "https://duckduckgo.com/Ukraine_Air_Enterprise",
         "Text" : "Ukraine A government-owned airline based in Kiev, Ukraine."
      },
      {
         "Result" : "<a href=\"https://duckduckgo.com/Ukraina_Stadium\">Ukraine</a>A multi-purpose stadium in Lviv, Ukraine.",
         "Icon" : {
            "URL" : "https://duckduckgo.com/i/59f85f9c.jpg",
            "Height" : "",
            "Width" : ""
         },
         "FirstURL" : "https://duckduckgo.com/Ukraina_Stadium",
         "Text" : "Ukraine A multi-purpose stadium in Lviv, Ukraine."
      },
      {
         "Result" : "<a href=\"https://duckduckgo.com/Palace_%22Ukraine%22\">Ukraine</a>National Palace of Arts \"Ukraina\" or Palace \"Ukraina\" is one of the main theatre venues for...",
         "Icon" : {
            "URL" : "https://duckduckgo.com/i/palace-ukraina.kiev.ua.ico",
            "Height" : 16,
            "Width" : 16
         },
         "FirstURL" : "https://duckduckgo.com/Palace_%22Ukraine%22",
         "Text" : "Ukraine National Palace of Arts \"Ukraina\" or Palace \"Ukraina\" is one of the main theatre venues for..."
      },
      {
         "Result" : "<a href=\"https://duckduckgo.com/Ukraina%2C_%C5%81%C3%B3d%C5%BA_Voivodeship\">Ukraina</a>A village in the administrative district of Gmina Zgierz, within Zgierz County, \u0141\u00f3d\u017a Voivodeship...",
         "Icon" : {
            "URL" : "",
            "Height" : "",
            "Width" : ""
         },
         "FirstURL" : "https://duckduckgo.com/Ukraina%2C_%C5%81%C3%B3d%C5%BA_Voivodeship",
         "Text" : "Ukraina A village in the administrative district of Gmina Zgierz, within Zgierz County, \u0141\u00f3d\u017a Voivodeship..."
      },
      {
         "Result" : "<a href=\"https://duckduckgo.com/Ukraina%2C_Lesser_Poland_Voivodeship\">Ukraina</a>A village in the administrative district of Gmina Biecz, within Gorlice County, Lesser Poland...",
         "Icon" : {
            "URL" : "",
            "Height" : "",
            "Width" : ""
         },
         "FirstURL" : "https://duckduckgo.com/Ukraina%2C_Lesser_Poland_Voivodeship",
         "Text" : "Ukraina A village in the administrative district of Gmina Biecz, within Gorlice County, Lesser Poland..."
      },
      {
         "Result" : "<a href=\"https://duckduckgo.com/Reichskommissariat_Ukraine\">Reichskommissariat Ukraine</a>The civilian occupation regime of much of German-occupied Ukraine.",
         "Icon" : {
            "URL" : "https://duckduckgo.com/i/dfd345b7.png",
            "Height" : "",
            "Width" : ""
         },
         "FirstURL" : "https://duckduckgo.com/Reichskommissariat_Ukraine",
         "Text" : "Reichskommissariat Ukraine The civilian occupation regime of much of German-occupied Ukraine."
      },
      {
         "Result" : "<a href=\"https://duckduckgo.com/Ukrainian_State\">Ukrainian State</a>An anti-socialist government that existed on most of territory of Ukraine from 29 April 1918 till...",
         "Icon" : {
            "URL" : "https://duckduckgo.com/i/0628d225.png",
            "Height" : "",
            "Width" : ""
         },
         "FirstURL" : "https://duckduckgo.com/Ukrainian_State",
         "Text" : "Ukrainian State An anti-socialist government that existed on most of territory of Ukraine from 29 April 1918 till..."
      },
      {
         "Result" : "<a href=\"https://duckduckgo.com/1709_Ukraina\">1709 Ukraina</a>A stony asteroid from the inner regions of the asteroid belt, approximately 10 kilometers in...",
         "Icon" : {
            "URL" : "",
            "Height" : "",
            "Width" : ""
         },
         "FirstURL" : "https://duckduckgo.com/1709_Ukraina",
         "Text" : "1709 Ukraina A stony asteroid from the inner regions of the asteroid belt, approximately 10 kilometers in..."
      },
      {
         "Topics" : [
            {
               "Result" : "<a href=\"https://duckduckgo.com/d/Ukraina\">Ukraina Meanings</a>  (transliteration from Ukrainian).",
               "Icon" : {
                  "URL" : "",
                  "Height" : "",
                  "Width" : ""
               },
               "FirstURL" : "https://duckduckgo.com/d/Ukraina",
               "Text" : "Ukraina Meanings (transliteration from Ukrainian)."
            },
            {
               "Result" : "<a href=\"https://duckduckgo.com/d/Ukrainian\">Ukrainian Meanings</a>  See related meanings for the word 'Ukrainian'.",
               "Icon" : {
                  "URL" : "",
                  "Height" : "",
                  "Width" : ""
               },
               "FirstURL" : "https://duckduckgo.com/d/Ukrainian",
               "Text" : "Ukrainian Meanings See related meanings for the word 'Ukrainian'."
            }
         ],
         "Name" : "See also"
      }
   ],
   "Entity" : "",
   "meta" : {
      "maintainer" : {
         "github" : "duckduckgo"
      },
      "perl_module" : "DDG::Fathead::Wikipedia",
      "status" : "live",
      "production_state" : "offline",
      "dev_date" : null,
      "js_callback_name" : "wikipedia",
      "signal_from" : "wikipedia_fathead",
      "live_date" : null,
      "src_id" : 1,
      "src_options" : {
         "skip_end" : "0",
         "skip_abstract" : 0,
         "skip_qr" : "",
         "language" : "en",
         "skip_icon" : 0,
         "skip_image_name" : 0,
         "directory" : "",
         "min_abstract_length" : "20",
         "skip_abstract_paren" : 0,
         "is_wikipedia" : 1,
         "source_skip" : "",
         "is_fanon" : 0,
         "is_mediawiki" : 1,
         "src_info" : ""
      },
      "repo" : "fathead",
      "developer" : [
         {
            "url" : "http://www.duckduckhack.com",
            "name" : "DDG Team",
            "type" : "ddg"
         }
      ],
      "tab" : "About",
      "producer" : null,
      "unsafe" : 0,
      "id" : "wikipedia_fathead",
      "dev_milestone" : "live",
      "topic" : [
         "productivity"
      ],
      "name" : "Wikipedia",
      "attribution" : null,
      "created_date" : null,
      "example_query" : "nikola tesla",
      "description" : "Wikipedia",
      "is_stackexchange" : null,
      "designer" : null,
      "src_domain" : "en.wikipedia.org",
      "src_name" : "Wikipedia",
      "blockgroup" : null,
      "src_url" : null
   },
   "Type" : "D",
   "Redirect" : "",
   "DefinitionURL" : "",
   "AbstractURL" : "https://en.wikipedia.org/wiki/Ukraine_(disambiguation)",
   "Definition" : "",
   "AbstractSource" : "Wikipedia",
   "Infobox" : "",
   "Image" : "",
   "ImageIsLogo" : 0,
   "Abstract" : "",
   "AbstractText" : "",
   "AnswerType" : "",
   "ImageHeight" : 0,
   "Answer" : "",
   "Results" : []
}